subtitle_ai_translator/__init__.py
subtitle_ai_translator/main.py
subtitle_ai_translator-1.0.dist-info/LICENSE
subtitle_ai_translator-1.0.dist-info/METADATA
subtitle_ai_translator-1.0.dist-info/WHEEL
subtitle_ai_translator-1.0.dist-info/entry_points.txt
subtitle_ai_translator-1.0.dist-info/top_level.txt
subtitle_ai_translator-1.0.dist-info/RECORD
