Metadata-Version: 2.1
Name: subtitle-ai-translator
Version: 1.0
Summary: AI-powered tool for seamless subtitle translation, enabling cross-language accessibility for video content.
Home-page: https://github.com/sutasrof/Subtitle-AI-Translator
Author: sutasrof
Author-email: mario.chauvet@icloud.com
Classifier: Programming Language :: Python :: 3
Classifier: License :: OSI Approved :: GNU General Public License v3 or later (GPLv3+)
Classifier: Operating System :: OS Independent
Requires-Python: >=3.6
License-File: LICENSE
Requires-Dist: transformers[torch] >=4.34.1
Requires-Dist: sentencepiece >=0.1.99
